cookapps_datacenter/__init__.py
cookapps_datacenter/config.py
cookapps_datacenter/data_center.py
cookapps_datacenter-0.0.22.dist-info/METADATA
cookapps_datacenter-0.0.22.dist-info/WHEEL
cookapps_datacenter-0.0.22.dist-info/top_level.txt
cookapps_datacenter-0.0.22.dist-info/RECORD
