Metadata-Version: 2.1
Name: cookapps-datacenter
Version: 0.0.22
Summary: CookApps DATACENTER SDK
Author: synoh
Author-email: syno@cookapps.com
Keywords: cookapps,aws,datacenter
Classifier: Programming Language :: Python :: 3.7
Requires-Python: >=3
Requires-Dist: pandas
Requires-Dist: boto3
